neofs_testlib_plugin_sbercloud/__init__.py
neofs_testlib_plugin_sbercloud/sbercloud_auth_requests.py
neofs_testlib_plugin_sbercloud/sbercloud_client.py
neofs_testlib_plugin_sbercloud/sbercloud_host.py
neofs_testlib_plugin_sbercloud-1.0.1.dist-info/LICENSE
neofs_testlib_plugin_sbercloud-1.0.1.dist-info/METADATA
neofs_testlib_plugin_sbercloud-1.0.1.dist-info/WHEEL
neofs_testlib_plugin_sbercloud-1.0.1.dist-info/entry_points.txt
neofs_testlib_plugin_sbercloud-1.0.1.dist-info/top_level.txt
neofs_testlib_plugin_sbercloud-1.0.1.dist-info/RECORD
