Metadata-Version: 2.1
Name: neofs-testlib-plugin-sbercloud
Version: 1.0.1
Summary: NeoFS testlib plugin providing host management functionality for cloud provider Sbercloud
Author-email: NSPCC <info@nspcc.ru>
License: GNU General Public License v3 (GPLv3)
Project-URL: Homepage, https://github.com/nspcc-dev/neofs-testlib-plugin-sbercloud
Keywords: neofs,test
Classifier: License :: OSI Approved :: GNU General Public License v3 (GPLv3)
Classifier: Programming Language :: Python
Classifier: Programming Language :: Python :: 3
Requires-Python: ==3.10.*
License-File: LICENSE
Requires-Dist: neofs-testlib (>=1.1.1)
Requires-Dist: requests (>=2.28.0)
Provides-Extra: dev
Requires-Dist: black ; extra == 'dev'
Requires-Dist: bumpver ; extra == 'dev'
Requires-Dist: isort ; extra == 'dev'
Requires-Dist: pre-commit ; extra == 'dev'
